[
    {
        "author": "D", 
        "isbn": "0596516487", 
        "id": "0", 
        "title": "O Dojo: The Definitive Guide"
    }, 
    {
        "author": "A", 
        "isbn": "0132358042", 
        "id": "1", 
        "title": "Dojo: Using the Dojo JavaScript Library to Build Ajax Applications"
    }, 
    {
        "title": "Practical Dojo Projects (Expert's Voice in Web Development)", 
        "isbn": "1430210664", 
        "id": "2", 
        "author": "A"
    }, 
    {
        "title": "The Dojo Toolkit: Visual QuickStart Guide", 
        "isbn": "0321605128", 
        "id": "3", 
        "author": "A"
    }, 
    {
        "title": "P Mastering Dojo: JavaScript and Ajax Tools for Great Web Experiences", 
        "isbn": "1934356115", 
        "id": "4", 
        "author": "DD"
    }
]